gulagcleaner/__init__.py
gulagcleaner/command_line.py
gulagcleaner/gulagcleaner_extract.py
gulagcleaner_xv-0.5.0.dist-info/LICENSE
gulagcleaner_xv-0.5.0.dist-info/METADATA
gulagcleaner_xv-0.5.0.dist-info/WHEEL
gulagcleaner_xv-0.5.0.dist-info/entry_points.txt
gulagcleaner_xv-0.5.0.dist-info/top_level.txt
gulagcleaner_xv-0.5.0.dist-info/RECORD
