Metadata-Version: 2.1
Name: gulagcleaner-xv
Version: 0.5.0
Summary: Herramienta de eliminación de anuncios para PDFs generados por la plataforma Wuolah.
Home-page: https://github.com/YoSoyGodot/gulag-cleaner-cli
Author: YM162,KosmicKatXV
Author-email: david.fontaneda@estudiante.uam.es
Project-URL: Bug Tracker, https://github.com/YoSoyGodot/gulag-cleaner-cli/issues
Classifier: Programming Language :: Python :: 3
Classifier: License :: OSI Approved :: MIT License
Classifier: Operating System :: OS Independent
Requires-Python: >=3.6
License-File: LICENSE
Requires-Dist: pdfrw (>=0.4)
Requires-Dist: pikepdf (>=5.1.2)
Requires-Dist: pdfminer.six (>=20220524)
